surfaces_cec_data/__init__.py
surfaces_cec_data/cec2013/__init__.py
surfaces_cec_data/cec2013/cec2013_data_dim10.npz
surfaces_cec_data/cec2013/cec2013_data_dim100.npz
surfaces_cec_data/cec2013/cec2013_data_dim2.npz
surfaces_cec_data/cec2013/cec2013_data_dim20.npz
surfaces_cec_data/cec2013/cec2013_data_dim30.npz
surfaces_cec_data/cec2013/cec2013_data_dim40.npz
surfaces_cec_data/cec2013/cec2013_data_dim5.npz
surfaces_cec_data/cec2013/cec2013_data_dim50.npz
surfaces_cec_data/cec2013/cec2013_data_dim60.npz
surfaces_cec_data/cec2013/cec2013_data_dim70.npz
surfaces_cec_data/cec2013/cec2013_data_dim80.npz
surfaces_cec_data/cec2013/cec2013_data_dim90.npz
surfaces_cec_data/cec2014/__init__.py
surfaces_cec_data/cec2014/cec2014_data_dim10.npz
surfaces_cec_data/cec2014/cec2014_data_dim100.npz
surfaces_cec_data/cec2014/cec2014_data_dim20.npz
surfaces_cec_data/cec2014/cec2014_data_dim30.npz
surfaces_cec_data/cec2014/cec2014_data_dim50.npz
surfaces_cec_data/cec2017/__init__.py
surfaces_cec_data/cec2017/cec2017_data_dim10.npz
surfaces_cec_data/cec2017/cec2017_data_dim100.npz
surfaces_cec_data/cec2017/cec2017_data_dim2.npz
surfaces_cec_data/cec2017/cec2017_data_dim20.npz
surfaces_cec_data/cec2017/cec2017_data_dim30.npz
surfaces_cec_data/cec2017/cec2017_data_dim50.npz
surfaces_cec_data-0.0.1.dist-info/METADATA
surfaces_cec_data-0.0.1.dist-info/WHEEL
surfaces_cec_data-0.0.1.dist-info/top_level.txt
surfaces_cec_data-0.0.1.dist-info/RECORD
