Metadata-Version: 2.4
Name: surfaces-cec-data
Version: 0.0.1
Summary: CEC benchmark data files for the surfaces library
Author-email: Simon Blanke <simon.blanke@yahoo.com>
License: MIT
Project-URL: Homepage, https://github.com/SimonBlanke/Surfaces
Project-URL: Bug Reports, https://github.com/SimonBlanke/Surfaces/issues
Keywords: optimization,benchmarks,CEC,surfaces
Classifier: Programming Language :: Python :: 3
Classifier: Programming Language :: Python :: 3.8
Classifier: Programming Language :: Python :: 3.9
Classifier: Programming Language :: Python :: 3.10
Classifier: Programming Language :: Python :: 3.11
Classifier: Programming Language :: Python :: 3.12
Classifier: License :: OSI Approved :: MIT License
Classifier: Operating System :: OS Independent
Classifier: Topic :: Scientific/Engineering :: Mathematics
Classifier: Intended Audience :: Science/Research
Requires-Python: >=3.8
